fakear/__init__.py
fakear/templates.py
tests/__init__.py
tests/run_py27.py
tests/run_py3.py
tests/test_basic.py
tests/test_e2e.py
tests/test_errors.py
fakear-0.1.2.dist-info/LICENCE.md
fakear-0.1.2.dist-info/METADATA
fakear-0.1.2.dist-info/WHEEL
fakear-0.1.2.dist-info/top_level.txt
fakear-0.1.2.dist-info/RECORD
