Metadata-Version: 2.1
Name: fakear
Version: 0.1.2
Summary: A Shell-command faker for Python Unit Testing
Home-page: UNKNOWN
Author: Franck LOURME
Author-email: flourme@scaleway.com
License: UNKNOWN
Platform: UNKNOWN
Classifier: Topic :: Software Development :: Testing
Classifier: Programming Language :: Python :: 2.7
Classifier: Programming Language :: Python :: 3
Classifier: License :: OSI Approved :: MIT License
Classifier: Operating System :: MacOS :: MacOS X
Classifier: Operating System :: POSIX :: Linux
Requires-Dist: pyyaml
Requires-Dist: voluptuous
